login_handler/__init__.py
login_handler/src/__init__.py
login_handler/src/configurations.py
login_handler/src/helpers.py
login_handler/src/user_types.py
login_handler/src/utils.py
login_handler/tests/__init__.py
login_handler/tests/conftest.py
login_handler/tests/test_cookies.py
login_handler/tests/test_login.py
login_handler/tests/test_with_remember_session.py
login_handler/tests/test_without_remember_session.py
login_handler/tests/utils.py
login_handler-0.0.1.dist-info/LICENSE.txt
login_handler-0.0.1.dist-info/METADATA
login_handler-0.0.1.dist-info/WHEEL
login_handler-0.0.1.dist-info/top_level.txt
login_handler-0.0.1.dist-info/RECORD
