Metadata-Version: 2.1
Name: login-handler
Version: 0.0.1
Summary: This module can be used to help in authentication and managing login/logout or sessions on the web
Home-page: https://github.com/PankajVishw50/login_handler.git
Author: Pankaj
Author-email: pankaj.vishw.dev@gmail.com
Classifier: Programming Language :: Python
Classifier: Programming Language :: Python :: 3 
Classifier: License :: OSI Approved :: MIT License
License-File: LICENSE.txt
Requires-Dist: cipher-kit (==0.0.4)
